CHANGES
LICENSE
MANIFEST.in
README.rst
requirements-tox.txt
requirements.txt
setup.py
py_configurator/__init__.py
py_configurator/config.py
py_configurator/locator.py
py_configurator.egg-info/PKG-INFO
py_configurator.egg-info/SOURCES.txt
py_configurator.egg-info/dependency_links.txt
py_configurator.egg-info/requires.txt
py_configurator.egg-info/top_level.txt
py_configurator/backends/__init__.py
py_configurator/backends/base.py
py_configurator/backends/dict.py
py_configurator/backends/ini.py
py_configurator/backends/yaml.py
tests/__init__.py
tests/test_config.py
tests/test_config_locator.py
tests/backends/__init__.py
tests/backends/test_dict.py
tests/backends/test_ini.py
tests/backends/test_provider.py
tests/backends/test_yaml.py