Metadata-Version: 1.1
Name: py-configurator
Version: 0.0.2
Summary: Tiny configuration wrapper module
Home-page: https://github.com/ryankanno/py-configurator
Author: Ryan Kanno
Author-email: ryankanno@localkinegrinds.com
License: MIT
Platform: UNKNOWN
Classifier: Development Status :: 3 - Alpha
Classifier: Intended Audience :: Developers
Classifier: Programming Language :: Python
Classifier: License :: OSI Approved :: MIT License
Classifier: Topic :: Utilities
